{
    "list":[
        {
            "id":"1",
            "name":"哲学"
        },
        {
            "id":"2",
            "name":"经济学"
        },
        {
            "id":"3",
            "name":"法学"
        },
        {
            "id":"4",
            "name":"教育学"
        },
        {
            "id":"5",
            "name":"文学"
        },
        {
            "id":"6",
            "name":"历史学"
        },
        {
            "id":"7",
            "name":"理学"
        },
        {
            "id":"8",
            "name":"工学"
        },
        {
            "id":"9",
            "name":"农学"
        },
        {
            "id":"10",
            "name":"医学"
        },
        {
            "id":"11",
            "name":"管理学"
        }
    ],
    "major":[
        {
            "id":"1",
            "name":"哲学相关类",
            "degree":"1"
        },
        {
            "id":"2",
            "name":"经济学相关类",
            "degree":"2"
        },
        {
            "id":"3",
            "name":"财政学相关类",
            "degree":"2"
        },
        {
            "id":"4",
            "name":"保险相关类",
            "degree":"2"
        },
        {
            "id":"5",
            "name":"金融相关类",
            "degree":"2"
        },
        {
            "id":"6",
            "name":"贸易相关类",
            "degree":"2"
        },
        {
            "id":"7",
            "name":"法学相关类",
            "degree":"3"
        },
        {
            "id":"8",
            "name":"马克思主义理论相关类",
            "degree":"3"
        },
        {
            "id":"9",
            "name":"社会学相关类",
            "degree":"3"
        },
        {
            "id":"10",
            "name":"政治学相关类",
            "degree":"3"
        },
        {
            "id":"11",
            "name":"公安学相关类",
            "degree":"3"
        },
        {
            "id":"12",
            "name":"教育学相关类",
            "degree":"4"
        },
        {
            "id":"13",
            "name":"小学教育相关类",
            "degree":"4"
        },
        {
            "id":"14",
            "name":"艺术教育相关类",
            "degree":"4"
        },
        {
            "id":"15",
            "name":"人文教育相关类",
            "degree":"4"
        },
        {
            "id":"16",
            "name":"科学教育相关类",
            "degree":"4"
        },
        {
            "id":"17",
            "name":"社会教育相关类",
            "degree":"4"
        },
        {
            "id":"18",
            "name":"体育学相关类",
            "degree":"4"
        },
        {
            "id":"19",
            "name":"中国语言文学相关类",
            "degree":"5"
        },
        {
            "id":"20",
            "name":"英语相关类",
            "degree":"5"
        },
        {
            "id":"21",
            "name":"俄语相关类",
            "degree":"5"
        },
        {
            "id":"22",
            "name":"德语相关类",
            "degree":"5"
        },
        {
            "id":"23",
            "name":"法语相关类",
            "degree":"5"
        },
        {
            "id":"24",
            "name":"西班牙语相关类",
            "degree":"5"
        },
        {
            "id":"25",
            "name":"阿拉伯语相关类",
            "degree":"5"
        },
        {
            "id":"26",
            "name":"日语相关类",
            "degree":"5"
        },
        {
            "id":"27",
            "name":"韩语相关类",
            "degree":"5"
        },
        {
            "id":"28",
            "name":"葡萄牙语相关类",
            "degree":"5"
        },
        {
            "id":"29",
            "name":"意大利语相关类",
            "degree":"5"
        },
        {
            "id":"30",
            "name":"其他外国语言文学相关类",
            "degree":"5"
        },
        {
            "id":"31",
            "name":"新闻传播学相关类",
            "degree":"5"
        },
        {
            "id":"32",
            "name":"艺术相关类",
            "degree":"5"
        },
        {
            "id":"33",
            "name":"历史学相关类",
            "degree":"6"
        },
        {
            "id":"34",
            "name":"数学相关类",
            "degree":"7"
        },
        {
            "id":"35",
            "name":"物理学相关类",
            "degree":"7"
        },
        {
            "id":"36",
            "name":"化学相关类",
            "degree":"7"
        },
        {
            "id":"37",
            "name":"生物科学相关类",
            "degree":"7"
        },
        {
            "id":"38",
            "name":"地理科学相关类",
            "degree":"7"
        },
        {
            "id":"39",
            "name":"地球物理学相关类",
            "degree":"7"
        },
        {
            "id":"40",
            "name":"大气科学相关类",
            "degree":"7"
        },
        {
            "id":"41",
            "name":"海洋科学相关类",
            "degree":"7"
        },
        {
            "id":"42",
            "name":"力学相关类",
            "degree":"7"
        },
        {
            "id":"43",
            "name":"电子相关类",
            "degree":"7"
        },
        {
            "id":"44",
            "name":"信息科学相关类",
            "degree":"7"
        },
        {
            "id":"45",
            "name":"材料科学相关类",
            "degree":"7"
        },
        {
            "id":"46",
            "name":"环境科学相关类",
            "degree":"7"
        },
        {
            "id":"47",
            "name":"心理学相关类",
            "degree":"7"
        },
        {
            "id":"48",
            "name":"统计学相关类",
            "degree":"7"
        },
        {
            "id":"49",
            "name":"天文学相关类",
            "degree":"7"
        },
        {
            "id":"50",
            "name":"地质学相关类",
            "degree":"7"
        },
        {
            "id":"51",
            "name":"系统科学相关类",
            "degree":"7"
        },
        {
            "id":"52",
            "name":"地矿相关类",
            "degree":"8"
        },
        {
            "id":"53",
            "name":"材料相关类",
            "degree":"8"
        },
        {
            "id":"54",
            "name":"机械相关类",
            "degree":"8"
        },
        {
            "id":"55",
            "name":"仪器仪表相关类",
            "degree":"8"
        },
        {
            "id":"56",
            "name":"能源动力相关类",
            "degree":"8"
        },
        {
            "id":"57",
            "name":"电气工程相关类",
            "degree":"8"
        },
        {
            "id":"58",
            "name":"信息工程相关类",
            "degree":"8"
        },
        {
            "id":"59",
            "name":"网络工程相关类",
            "degree":"8"
        },
        {
            "id":"60",
            "name":"通信工程相关类",
            "degree":"8"
        },
        {
            "id":"61",
            "name":"电子工程相关类",
            "degree":"8"
        },
        {
            "id":"62",
            "name":"计算机相关类",
            "degree":"8"
        },
        {
            "id":"63",
            "name":"土建相关类",
            "degree":"8"
        },
        {
            "id":"64",
            "name":"水利相关类",
            "degree":"8"
        },
        {
            "id":"65",
            "name":"测绘相关类",
            "degree":"8"
        },
        {
            "id":"66",
            "name":"环境与安全相关类",
            "degree":"8"
        },
        {
            "id":"67",
            "name":"化工与制药相关类",
            "degree":"8"
        },
        {
            "id":"68",
            "name":"交通运输相关类",
            "degree":"8"
        },
        {
            "id":"69",
            "name":"海洋工程相关类",
            "degree":"8"
        },
        {
            "id":"70",
            "name":"轻工纺织食品相关类",
            "degree":"8"
        },
        {
            "id":"71",
            "name":"航空航天相关类",
            "degree":"8"
        },
        {
            "id":"72",
            "name":"武器相关类",
            "degree":"8"
        },
        {
            "id":"73",
            "name":"工程力学相关类",
            "degree":"8"
        },
        {
            "id":"74",
            "name":"生物工程相关类",
            "degree":"8"
        },
        {
            "id":"75",
            "name":"农业工程相关类",
            "degree":"9"
        },
        {
            "id":"76",
            "name":"林业工程相关类",
            "degree":"9"
        },
        {
            "id":"77",
            "name":"公安技术相关类",
            "degree":"9"
        },
        {
            "id":"78",
            "name":"光电相关类",
            "degree":"9"
        },
        {
            "id":"79",
            "name":"电力电子相关类",
            "degree":"9"
        },
        {
            "id":"80",
            "name":"生物医学工程相关类",
            "degree":"9"
        },
        {
            "id":"81",
            "name":"植物生产相关类",
            "degree":"9"
        },
        {
            "id":"82",
            "name":"草业科学相关类",
            "degree":"9"
        },
        {
            "id":"83",
            "name":"森林资源相关类",
            "degree":"9"
        },
        {
            "id":"84",
            "name":"环境生态相关类",
            "degree":"9"
        },
        {
            "id":"85",
            "name":"动物生产相关类",
            "degree":"9"
        },
        {
            "id":"86",
            "name":"动物医学相关类",
            "degree":"9"
        },
        {
            "id":"87",
            "name":"水产相关类",
            "degree":"9"
        },
        {
            "id":"88",
            "name":"基础医学相关类",
            "degree":"10"
        },
        {
            "id":"89",
            "name":"预防医学相关类",
            "degree":"10"
        },
        {
            "id":"90",
            "name":"临床医学与医学技术相关类",
            "degree":"10"
        },
        {
            "id":"91",
            "name":"口腔医学相关类",
            "degree":"10"
        },
        {
            "id":"92",
            "name":"中医学相关类",
            "degree":"10"
        },
        {
            "id":"93",
            "name":"法医学相关类",
            "degree":"10"
        },
        {
            "id":"94",
            "name":"护理学相关类",
            "degree":"10"
        },
        {
            "id":"95",
            "name":"药学相关类",
            "degree":"10"
        },
        {
            "id":"96",
            "name":"放射医学相关类",
            "degree":"10"
        },
        {
            "id":"97",
            "name":"医学影像学相关类",
            "degree":"10"
        },
        {
            "id":"98",
            "name":"管理科学与工程相关类",
            "degree":"11"
        },
        {
            "id":"99",
            "name":"工商管理相关类",
            "degree":"11"
        },
        {
            "id":"100",
            "name":"市场营销相关类",
            "degree":"11"
        },
        {
            "id":"101",
            "name":"财会管理相关类",
            "degree":"11"
        },
        {
            "id":"102",
            "name":"人力资源管理相关类",
            "degree":"11"
        },
        {
            "id":"103",
            "name":"旅游管理相关类",
            "degree":"11"
        },
        {
            "id":"104",
            "name":"电子商务相关类",
            "degree":"11"
        },
        {
            "id":"105",
            "name":"物流管理相关类",
            "degree":"11"
        },
        {
            "id":"106",
            "name":"物业管理相关类",
            "degree":"11"
        },
        {
            "id":"107",
            "name":"公共管理相关类",
            "degree":"11"
        },
        {
            "id":"108",
            "name":"农业经济管理相关类",
            "degree":"11"
        },
        {
            "id":"109",
            "name":"图书档案学相关类",
            "degree":"11"
        }
    ]
}